{
  "Mechanic":[
    {"name":"טכנאי נשק וצריח מרכבה 4","videoUrl":null,"textPath":"rakia.html"},
    {"name":"טכנאי נשק וצריח מרכבה 2,3","videoUrl":null,"textPath":"rakia.html"},
    {"name":"טכנאי נשק וצריח תומ\"ת","videoUrl":null,"textPath":"yaad.html"},
    {"name":"טכנאי מערכות הנעה מרכבה 4","videoUrl":null,"textPath":"marom.html"},
    {"name":"טכנאי מערכות הנעה מרכבה 2,3","videoUrl":null,"textPath":"proyektantim.html"},
    {"name":"טכנאי מערכות הנעה נמר","videoUrl":null,"textPath":"kakatzyashir.html"},
    {"name":"טכנאי מערכות הנעה פומ\"ה","videoUrl":null,"textPath":"yahalom.html"},
    {"name":"טכנאי מערכות הנעה וחשמל נגמ\"ש","videoUrl":null,"textPath":"shoham.html"},
    {"name":"טכנאי מערכות הנעה צמ\"ה","videoUrl":null,"textPath":"bareket.html"},
    {"name":"טכנאי מערכות הנעה תומ\"ת","videoUrl":null,"textPath":"shoharut.html"},
    {"name":"טכנאי מערכות הנעה אכזרית","videoUrl":null,"textPath":"shoharut.html"},
    {"name":"טכנאי תובה מנת\"ץ","videoUrl":null,"textPath":"shoharut.html"}
  ],
  "Electronic":[
    {"name":"טכנאי בקרה ותצפית מרכבה 4","videoUrl":null,"textPath":"hov.html"},
    {"name":"טכנאי בקרת אש מרכבה 2,3","videoUrl":null,"textPath":"rakia.html"},
    {"name":"טכנאי מערכות (ב\"ז)","videoUrl":null,"textPath":"yaad.html"},
    {"name":"טכנאי מערכות אלקטרוניות נמר","videoUrl":null,"textPath":"marom.html"},
    {"name":"מערכות יעודית מנת\"ץ","videoUrl":null,"textPath":"proyektantim.html"},
    {"name":"טכאי מערכות טכנולוגיות מתקדמות","videoUrl":null,"textPath":"kakatzyashir.html"},
    {"name":"טכנאי בקרת אש תומ\"ת","videoUrl":null,"textPath":"yahalom.html"},
    {"name":"טכנאי מוד\"ש","videoUrl":null,"textPath":"shoham.html"},
    {"name":"אלקטרונאי טכנולוגיה ואחזקה","videoUrl":null,"textPath":"bareket.html"}
  ],
  "Cars":[
    {"name":"טכנאי רכב","videoUrl":null,"textPath":"hov.html"},
    {"name":"מאבחן מערכות רכב (מאמ\"ר)","videoUrl":null,"textPath":"rakia.html"}

  ]

}